text_indexer/__init__.py
text_indexer/io.py
text_indexer/indexers/__init__.py
text_indexer/indexers/base.py
text_indexer/indexers/char_indexer.py
text_indexer/indexers/pipe_indexer.py
text_indexer/indexers/utils.py
text_indexer/indexers/tests/__init__.py
text_indexer/indexers/tests/template.py
text_indexer/indexers/tests/test_char_indexer.py
text_indexer/indexers/tests/data/example.json
text_indexer/indexers/tests/data/example.msg
text_indexer/tests/__init__.py
text_indexer/tests/test_io.py
text_indexer-1.1.1.dist-info/LICENSE
text_indexer-1.1.1.dist-info/METADATA
text_indexer-1.1.1.dist-info/WHEEL
text_indexer-1.1.1.dist-info/top_level.txt
text_indexer-1.1.1.dist-info/RECORD
