Metadata-Version: 2.1
Name: text-indexer
Version: 1.1.1
Summary: Yoctol Text Indexer
Home-page: https://github.com/Yoctol/text-indexer
Author: Yoctol Info
Author-email: yien.tsai@yoctol.com
License: MIT
Platform: UNKNOWN
Classifier: Programming Language :: Python
Classifier: Programming Language :: Python :: 3.6
Requires-Python: >=3.6
Requires-Dist: strpipe (==0.4.7)
Requires-Dist: u-msgpack-python (==2.5.0)
